usmo/__init__.py
usmo/cli.py
usmo-0.1.1.dist-info/METADATA
usmo-0.1.1.dist-info/WHEEL
usmo-0.1.1.dist-info/entry_points.txt
usmo-0.1.1.dist-info/RECORD
