Metadata-Version: 2.4
Name: usmo
Version: 0.1.1
Summary: Add your description here
Requires-Python: >=3.10
Requires-Dist: click>=8.2.1
Requires-Dist: requests>=2.32.4
Requires-Dist: rich>=14.0.0
